titanicpackagegna/__init__.py
titanicpackagegna/controler.py
titanicpackagegna/get_data.py
titanicpackagegna/model.py
titanicpackagegna/pipeline.py
titanicpackagegna/preprocessing.py
titanicpackagegna/response_json.py
titanicpackagegna/tests.py
titanicpackagegna-0.0.4.dist-info/LICENSE
titanicpackagegna-0.0.4.dist-info/METADATA
titanicpackagegna-0.0.4.dist-info/WHEEL
titanicpackagegna-0.0.4.dist-info/top_level.txt
titanicpackagegna-0.0.4.dist-info/RECORD
