Metadata-Version: 2.1
Name: titanicpackagegna
Version: 0.0.4
Summary: Notre premier package de machine learning
Home-page: UNKNOWN
Author: Nouha, Adrien, Gwendelina
Author-email: <gwendelina.prudhomme@gmail.com>
License: UNKNOWN
Keywords: python,titanic,ml,prediction,machine learning
Platform: UNKNOWN
Classifier: Development Status :: 1 - Planning
Classifier: Intended Audience :: Developers
Classifier: Programming Language :: Python :: 3
Classifier: Operating System :: Unix
Classifier: Operating System :: MacOS :: MacOS X
Classifier: Operating System :: Microsoft :: Windows
